ascends.py
ascends_toolkit-0.4.0.data/scripts/classify_with_model.py
ascends_toolkit-0.4.0.data/scripts/predict.py
ascends_toolkit-0.4.0.data/scripts/predict_with_model.py
ascends_toolkit-0.4.0.data/scripts/train.py
ascends_toolkit-0.4.0.data/scripts/train_classifier.py
ascends_toolkit-0.4.0.data/scripts/train_regression.py
ascends_toolkit-0.4.0.dist-info/LICENSE
ascends_toolkit-0.4.0.dist-info/METADATA
ascends_toolkit-0.4.0.dist-info/WHEEL
ascends_toolkit-0.4.0.dist-info/top_level.txt
ascends_toolkit-0.4.0.dist-info/RECORD
